LICENSE
MANIFEST.in
README.rst
requirements.txt
setup.py
candv_x/__init__.py
candv_x/django/__init__.py
candv_x/django/choices/__init__.py
candv_x/django/choices/admin.py
candv_x/django/choices/db.py
candv_x/django/choices/forms.py
candv_x/django/choices/widgets.py
django_candv_choices.egg-info/PKG-INFO
django_candv_choices.egg-info/SOURCES.txt
django_candv_choices.egg-info/dependency_links.txt
django_candv_choices.egg-info/namespace_packages.txt
django_candv_choices.egg-info/requires.txt
django_candv_choices.egg-info/top_level.txt