Metadata-Version: 1.1
Name: django-candv-choices
Version: 1.1.5
Summary: Use complex constants built with 'candv' library instead of standard 'choices' fields for 'Django' models.
Home-page: https://github.com/oblalex/django-candv-choices
Author: Alexander Oblovatniy
Author-email: oblovatniy@gmail.com
License: LGPLv3
Keywords: choices,constants,Django,candv,values
Platform: any
Classifier: Development Status :: 5 - Production/Stable
Classifier: Intended Audience :: Developers
Classifier: License :: OSI Approved :: GNU Lesser General Public License v3 (LGPLv3)
Classifier: Natural Language :: English
Classifier: Operating System :: OS Independent
Classifier: Programming Language :: Python :: 2.7
Classifier: Programming Language :: Python :: 3.4
Classifier: Topic :: Software Development :: Libraries
